homopolymer_compression.cpython-36m-darwin.so
tiptoft/Blocks.py
tiptoft/Fasta.py
tiptoft/Fastq.py
tiptoft/Gene.py
tiptoft/InputTypes.py
tiptoft/Kmers.py
tiptoft/Read.py
tiptoft/RefGenesGetter.py
tiptoft/TipToft.py
tiptoft/TipToftDatabaseDownloader.py
tiptoft/__init__.py
tiptoft/data/20180928.txt
tiptoft/data/plasmid_data.fa
tiptoft/data/plasmid_data.tsv
tiptoft-1.0.2.data/scripts/tiptoft
tiptoft-1.0.2.data/scripts/tiptoft_database_downloader
tiptoft-1.0.2.dist-info/DESCRIPTION.rst
tiptoft-1.0.2.dist-info/METADATA
tiptoft-1.0.2.dist-info/RECORD
tiptoft-1.0.2.dist-info/WHEEL
tiptoft-1.0.2.dist-info/metadata.json
tiptoft-1.0.2.dist-info/top_level.txt
