Metadata-Version: 2.0
Name: tiptoft
Version: 1.0.2
Summary: tiptoft: predict which plasmid should be present from uncorrected long read data
Home-page: https://github.com/andrewjpage/tiptoft
Author: Andrew J. Page
Author-email: andrew.page@quadram.ac.uk
License: GPLv3
Platform: UNKNOWN
Classifier: Development Status :: 4 - Beta
Classifier: Intended Audience :: Science/Research
Classifier: Topic :: Scientific/Engineering :: Bio-Informatics
Classifier: Programming Language :: Python :: 3 :: Only
Classifier: License :: OSI Approved :: GNU General Public License v3 (GPLv3)
Requires-Dist: biopython (>=1.68)
Requires-Dist: pyfastaq (>=3.12.0)
Requires-Dist: cython
